PowerPy/App.py
PowerPy/Dashboard.py
PowerPy/Dataflow.py
PowerPy/Dataset.py
PowerPy/PowerPy.py
PowerPy/PowerPyObject.py
PowerPy/Report.py
PowerPy/RestConnector.py
PowerPy/Tenant.py
PowerPy/User.py
PowerPy/Utils.py
PowerPy/Workbook.py
PowerPy/Workspace.py
PowerPy/__init__.py
PowerPySDK-0.0.5.dist-info/LICENSE
PowerPySDK-0.0.5.dist-info/METADATA
PowerPySDK-0.0.5.dist-info/WHEEL
PowerPySDK-0.0.5.dist-info/top_level.txt
PowerPySDK-0.0.5.dist-info/RECORD
