Metadata-Version: 2.1
Name: PowerPySDK
Version: 0.0.5
Summary: An sdk for working with the Power Platform API
Author-email: Nathan Giusti <nathanggiusti@gmail.com>
License: GNU GENERAL PUBLIC LICENSE
Classifier: Programming Language :: Python :: 3
Classifier: License :: OSI Approved :: MIT License
Classifier: Operating System :: OS Independent
Requires-Python: >=3.7
License-File: LICENSE
Requires-Dist: PyYAML (>=5.4.1)
Requires-Dist: requests (>=2.26.0)
